LRstats/__init__.py
LRstats/descriptive.py
LRstats/inferential.py
LRstats/utils.py
LRstats-0.0.3.dist-info/LICENSE
LRstats-0.0.3.dist-info/METADATA
LRstats-0.0.3.dist-info/WHEEL
LRstats-0.0.3.dist-info/top_level.txt
LRstats-0.0.3.dist-info/RECORD
