Metadata-Version: 2.1
Name: LRstats
Version: 0.0.3
Summary: Computing statistic for longrun
Home-page: https://gitlab.com/salvatore.causio/longrun_statistics.git
Author: Salvatore Causio
Author-email: salvatore.causio@cmcc.it
License: UNKNOWN
Platform: UNKNOWN
Classifier: Programming Language :: Python :: 3
Classifier: License :: OSI Approved :: MIT License
Classifier: Operating System :: OS Independent
